brisksec_toolbox_wrapper_sdk/__init__.py
brisksec_toolbox_wrapper_sdk/parser.py
brisksec_toolbox_wrapper_sdk/wrapper.py
brisksec_toolbox_wrapper_sdk/types/__init__.py
brisksec_toolbox_wrapper_sdk/types/asset_events.py
brisksec_toolbox_wrapper_sdk/types/events.py
brisksec_toolbox_wrapper_sdk/types/findings.py
examples/__init__.py
examples/integration.py
tests/__init__.py
tests/test_types.py
brisksec_toolbox_wrapper_sdk-1.2025.627.519.dist-info/METADATA
brisksec_toolbox_wrapper_sdk-1.2025.627.519.dist-info/WHEEL
brisksec_toolbox_wrapper_sdk-1.2025.627.519.dist-info/top_level.txt
brisksec_toolbox_wrapper_sdk-1.2025.627.519.dist-info/RECORD
