Metadata-Version: 2.4
Name: brisksec_toolbox_wrapper_sdk
Version: 1.2025.627.519
Summary: Simplified BriskSec Toolbox Wrapper SDK for Python - focused on output parsing and event generation
Author-email: BriskSec <info@brisksec.com>
License-Expression: MIT
Project-URL: Homepage, https://github.com/brisksec/wrapper
Project-URL: Repository, https://github.com/brisksec/wrapper
Project-URL: Issues, https://github.com/brisksec/wrapper/issues
Classifier: Development Status :: 4 - Beta
Classifier: Intended Audience :: Developers
Classifier: Programming Language :: Python :: 3
Classifier: Programming Language :: Python :: 3.7
Classifier: Programming Language :: Python :: 3.8
Classifier: Programming Language :: Python :: 3.9
Classifier: Programming Language :: Python :: 3.10
Classifier: Programming Language :: Python :: 3.11
Requires-Python: >=3.7
Requires-Dist: pydantic>=1.8.0
Provides-Extra: dev
Requires-Dist: pytest>=6.0.0; extra == "dev"
Requires-Dist: black>=21.5b2; extra == "dev"
Requires-Dist: isort>=5.9.1; extra == "dev"
Requires-Dist: mypy>=0.812; extra == "dev"
